{
  "WF": "Wallis ma Futuna",
  "JP": "Iapani",
  "JM": "Jamaica",
  "JO": "Jordan",
  "WS": "Samoa",
  "JE": "Jersey",
  "GW": "Guinea-Bissau",
  "GU": "Guam",
  "GT": "Guatemala",
  "GS": "South Georgia ma South Sandwich Islands",
  "GR": "Greece",
  "GQ": "Equatorial Guinea",
  "GP": "Guadeloupe",
  "GY": "Guyana",
  "GG": "Guernsey",
  "GF": "Farani Farani",
  "GE": "Georgia",
  "GD": "Grenada",
  "GB": "Peletania",
  "GA": "Gabon",
  "GN": "Guinea",
  "GM": "Gambia",
  "GL": "Greenland",
  "GI": "Gibraltar",
  "GH": "Ghana",
  "PR": "Puerto Rico",
  "PS": "Palemia Teritori, Nofo",
  "PW": "Palau",
  "PT": "Portugal",
  "PY": "Paraguay",
  "PA": "Panama",
  "PF": "French Polynesia",
  "PG": "Papua Niu Kini",
  "PE": "Peru",
  "PK": "Pakistan",
  "PH": "Filipino",
  "PN": "Pitcairn",
  "PL": "Polani",
  "PM": "Saint Pierre ma Miquelon",
  "ZM": "Zambia",
  "ZA": "Afelika i Saute",
  "ZW": "Zimbabwe",
  "ME": "Montenegro",
  "MD": "Moldova, Republic of",
  "MG": "Madagascar",
  "MF": "Saint Martin (vaega Farani)",
  "MA": "Morocco",
  "MC": "Monaco",
  "MM": "Myanmar",
  "ML": "Mali",
  "MO": "Macao",
  "MN": "Mongolia",
  "MH": "Marshall Islands",
  "MK": "Maketonia, Republic of",
  "MU": "Mauritius",
  "MT": "Malta",
  "MW": "Malawi",
  "MV": "Maldives",
  "MQ": "Martinique",
  "MP": "Aitu Mariana i Matu",
  "MS": "Montserrat",
  "MR": "Mauritania",
  "MY": "Malasia",
  "MX": "Mesiko",
  "MZ": "Mozambique",
  "FR": "Falani",
  "FI": "Finland",
  "FJ": "Fiti",
  "FK": "Motu Falkland (Malvinas)",
  "FM": "Micronesia, Federated States of",
  "FO": "Faroe Islands",
  "CK": "Aitu Kuki",
  "CI": "Cote d&#39;Ivoire",
  "CH": "Sueteselani",
  "CO": "Colombia",
  "CN": "Saina",
  "CM": "Cameroon",
  "CL": "Chile",
  "CC": "Cocos (Keeling) Islands",
  "CA": "Kanata",
  "CG": "Congo",
  "CF": "Central African Republic",
  "CD": "Congo, Le Democratic Republic of the",
  "CZ": "Czech Republic",
  "CY": "Cyprus",
  "CX": "Kerisimasi Motu",
  "CR": "Costa Rica",
  "CW": "Cura\u00e7ao",
  "CV": "Cape Verde",
  "CU": "Cuba",
  "SZ": "Swaziland",
  "SY": "Suria Arab Republic",
  "SX": "Sint Maarten (Italia)",
  "SS": "South Sudan",
  "SR": "Suriname",
  "SV": "El Salvador",
  "ST": "Sao Tome and Principe",
  "SK": "Slovaki",
  "SJ": "Svalbard ma Jan Mayen",
  "SI": "Slovenia",
  "SH": "Saint Helena, Ascension ma Tristan da Cunha",
  "SO": "Somalia",
  "SN": "Senegal",
  "SM": "San Marino",
  "SL": "Sierra Leone",
  "SC": "Seychelles",
  "SB": "Aitu Solomono",
  "SA": "Saudi Alapi",
  "SG": "Singapore",
  "SE": "Sweden",
  "SD": "Sudan",
  "YE": "Yemen",
  "YT": "Mayotte",
  "LB": "Lebanon",
  "LC": "Saint Lucia",
  "LA": "Lao People&#39;s Democratic Republic",
  "LK": "Sri Lanka",
  "LI": "Liechtenstein",
  "LV": "Latvia",
  "LT": "Lithuania",
  "LU": "Luxembourg",
  "LR": "Liberia",
  "LS": "Lesotho",
  "LY": "Libya",
  "VA": "Holy See (Vatican City State)",
  "VC": "Saint Vincent and the Grenadines",
  "VE": "Venezuela, Bolivarian Republic of",
  "VG": "Virgin Islands, Peretania",
  "IQ": "Iraq",
  "VI": "Virgin Islands, US",
  "IS": "Aiselani",
  "IR": "Iran, Islamic Republic of",
  "IT": "Italia",
  "VN": "Vietnam",
  "IM": "Isle of Man",
  "IL": "Isalaeru",
  "IO": "Itumalo o Peretania Initia Initia",
  "IN": "Initia",
  "IE": "Aialani",
  "ID": "Ikonisia",
  "BD": "Bangladesh",
  "BE": "Belgium",
  "BF": "Burkina Faso",
  "BG": "Bulgaria",
  "BA": "Bosnia and Herzegovina",
  "BB": "Barbados",
  "BL": "Saint Barth\u00e9lemy",
  "BM": "Bermuda",
  "BN": "Brunei Darussalam",
  "BO": "Bolivia, Atina\u02bbe o le",
  "BH": "Bahrain",
  "BI": "Burundi",
  "BJ": "Benin",
  "BT": "Bhutan",
  "BV": "Bouvet Island",
  "BW": "Botswana",
  "BQ": "Bonaire, Sint Eustatius ma Saba",
  "BR": "Brazil",
  "BS": "Bahamas",
  "BY": "Belarus",
  "BZ": "Belize",
  "RU": "Russian Federation",
  "RW": "Rwanda",
  "RS": "Serbia",
  "RE": "Fa\u02bbapotopotoga",
  "RO": "Romania",
  "OM": "Oman",
  "HR": "Croatia",
  "HT": "Haiti",
  "HU": "Hungary",
  "HK": "Hong Kong",
  "HN": "Honduras",
  "HM": "Fa\u02bbalogo Island ma McDonald Islands",
  "EH": "Western Sahara",
  "EE": "Estonia",
  "EG": "Aikupito",
  "EC": "Ecuador",
  "ET": "Ethiopia",
  "ES": "Spain",
  "ER": "Eritrea",
  "UY": "Uruguay",
  "UZ": "Uzbekistan",
  "US": "Amerika Tele",
  "UM": "Iunaite Setete Atumotu o lo\u02bbo i fafo",
  "UG": "Uganda",
  "UA": "Ukraine",
  "VU": "Vanuatu",
  "NI": "Nicaragua",
  "NL": "Netherlands",
  "NO": "Norway",
  "NA": "Namibia",
  "NC": "New Caledonia",
  "NE": "Niger",
  "NF": "Aitu o Norfolk",
  "NG": "Nigeria",
  "NZ": "Niu Sila",
  "NP": "Nepal",
  "NR": "Nauru",
  "NU": "Niue",
  "KG": "Kyrgzstan",
  "KE": "Kenya",
  "KI": "Kiripati",
  "KH": "Cambodia",
  "KN": "Saint Kitts and Nevis",
  "KM": "Comoros",
  "KR": "Korea, Republic of",
  "KP": "Korea, Democratic Republic of the Republic o",
  "KW": "Kuaki",
  "KZ": "Kazakhstan",
  "KY": "Cayman Islands",
  "DO": "Dominican Republic",
  "DM": "Dominica",
  "DJ": "Dijbouti",
  "DK": "Denmark",
  "DE": "Siamani",
  "DZ": "Algeria",
  "TZ": "Tanzania, United Republic o",
  "TV": "Tuvalu",
  "TW": "Taiwan, Province o Saina",
  "TT": "Trinidad and Tobago",
  "TR": "Turkey",
  "TN": "Tunisia",
  "TO": "Tonga",
  "TL": "Timor-Leste",
  "TM": "Turkmenistan",
  "TJ": "Tajikistan",
  "TK": "Tokelau",
  "TH": "Thailand",
  "TF": "French Southern Territories",
  "TG": "Togo",
  "TD": "Chad",
  "TC": "Turks ma Caicos Islands",
  "AE": "United Arab Emirates",
  "AD": "Andorra",
  "AG": "Antigua and Barbuda",
  "AF": "Afghanistan",
  "AI": "Anguilla",
  "AM": "Armenia",
  "AL": "Albania",
  "AO": "Angola",
  "AQ": "Antarctica",
  "AS": "Amerika Samoa",
  "AR": "Argentina",
  "AU": "Ausetalia",
  "AT": "Austria",
  "AW": "Aruba",
  "AX": "Aland Islands",
  "AZ": "Azerbaijan",
  "QA": "Qatar"
}