{
  "Atlantic/Canary": "Atlantycki / kanaryjski",
  "Australia/Melbourne": "Australia / Melbourne",
  "Europe/Lisbon": "Europa / Lizbona",
  "America/Nipigon": "Ameryka / Nipigon",
  "America/Miquelon": "Ameryka / Miquelon",
  "Pacific/Wallis": "Pacific / Wallis",
  "America/Fort_Nelson": "Ameryka / Fort_Nelson",
  "Antarctica/Davis": "Antarktyda / Davis",
  "Canada/Mountain": "Kanada / G\u00f3ra",
  "Asia/Dhaka": "Azja / Dhaka",
  "America/St_Lucia": "Ameryka / St_Lucia",
  "America/Phoenix": "Ameryka / Phoenix",
  "Asia/Kuwait": "Azja / Kuwejt",
  "America/Mazatlan": "Ameryka / Mazatlan",
  "Arctic/Longyearbyen": "Arctic / Longyearbyen",
  "Europe/Guernsey": "Europa / Guernsey",
  "Antarctica/Rothera": "Antarktyda / Rothera",
  "Europe/Stockholm": "Europa / Sztokholm",
  "Pacific/Fiji": "Pacyfik / Fid\u017ci",
  "Pacific/Apia": "Pacyfik / Apia",
  "Pacific/Pago_Pago": "Pacific / Pago_Pago",
  "America/Mexico_City": "Ameryka / Meksyk_City",
  "America/Puerto_Rico": "Ameryka / Puerto_Rico",
  "Indian/Mauritius": "Indyjski / Mauritius",
  "Asia/Yangon": "Azja / Yangon",
  "Europe/Berlin": "Europa / Berlin",
  "Europe/Zurich": "Europa / Zurych",
  "Africa/Casablanca": "Afryka / Casablanca",
  "Antarctica/Macquarie": "Antarktyda / Macquarie",
  "Europe/Warsaw": "Europa / Warszawa",
  "Asia/Krasnoyarsk": "Azja / Krasnojarsk",
  "Atlantic/Bermuda": "Atlantic / Bermudy",
  "America/Araguaina": "Ameryka / Araguaina",
  "Asia/Tehran": "Azja / Teheran",
  "Asia/Baku": "Azja / Baku",
  "America/St_Barthelemy": "Ameryka / St_Bartelemy",
  "America/Santarem": "Ameryka / Santarem",
  "America/Danmarkshavn": "Ameryka / Danmarkshavn",
  "America/Scoresbysund": "Ameryka / Scoresbysund",
  "America/Eirunepe": "Ameryka / Eirunepe",
  "America/Caracas": "Ameryka / Caracas",
  "Asia/Baghdad": "Azja / Bagdad",
  "Africa/Monrovia": "Afryka / Monrovia",
  "Atlantic/Stanley": "Atlantic / Stanley",
  "America/St_Vincent": "Ameryka / St_Vincent",
  "America/Vancouver": "Ameryka / Vancouver",
  "Asia/Ho_Chi_Minh": "Azja / Ho_Chi_Minh",
  "Europe/Busingen": "Europa / Busingen",
  "Asia/Thimphu": "Azja / Thimphu",
  "Africa/Ouagadougou": "Afryka / Ouagadougou",
  "America/Belize": "Ameryka / Belize",
  "America/Port_of_Spain": "Ameryka / Port_Spain",
  "Asia/Famagusta": "Azja / Famagusta",
  "Asia/Tashkent": "Azja / Taszkient",
  "Asia/Tokyo": "Azja / Tokio",
  "Pacific/Kiritimati": "Pacific / Kiritimati",
  "Australia/Sydney": "Australia / Sydney",
  "Europe/Riga": "Europa / Ryga",
  "Asia/Dili": "Azja / Dili",
  "Africa/Mbabane": "Afryka / Mbabane",
  "Asia/Oral": "Azja / Ustny",
  "Asia/Aden": "Azja / Aden",
  "Europe/Isle_of_Man": "Europe / Isle_of_Man",
  "Europe/Istanbul": "Europa / Stambu\u0142",
  "Asia/Magadan": "Azja / Magadan",
  "Australia/Lindeman": "Australia / Lindeman",
  "Pacific/Galapagos": "Pacific / Galapagos",
  "America/Bogota": "Ameryka / Bogota",
  "Africa/Asmara": "Afryka / Asmara",
  "America/Chicago": "Ameryka / Chicago",
  "Pacific/Kwajalein": "Pacific / Kwajalein",
  "Australia/Broken_Hill": "Australia / Broken_Hill",
  "America/Cuiaba": "Ameryka / Cuiaba",
  "Indian/Christmas": "Indyjski / Bo\u017ce Narodzenie",
  "Asia/Jayapura": "Azja / Jayapura",
  "Europe/Brussels": "Europa / Bruksela",
  "America/Argentina/Cordoba": "Ameryka / Argentyna / Cordoba",
  "Canada/Pacific": "Kanada / Pacyfik",
  "America/Noronha": "Ameryka / Noronha",
  "Europe/Podgorica": "Europa / Podgorica",
  "Africa/Algiers": "Afryka / Algier",
  "Africa/Harare": "Afryka / Harare",
  "Africa/Ndjamena": "Afryka / Nd\u017camena",
  "America/Costa_Rica": "Ameryka / Costa_Rica",
  "Europe/Ljubljana": "Europa / Lublana",
  "Indian/Mayotte": "Indyjska / majotka",
  "Asia/Phnom_Penh": "Azja / Phnom_Penh",
  "America/Managua": "Ameryka / Managua",
  "America/Pangnirtung": "Ameryka / Pangnirtung",
  "America/Tijuana": "Ameryka / Tijuana",
  "Pacific/Fakaofo": "Pacific / Fakaofo",
  "America/Martinique": "Ameryka / Martynika",
  "America/Antigua": "Ameryka / Antigua",
  "America/Indiana/Indianapolis": "Ameryka / Indiana / Indianapolis",
  "America/Argentina/La_Rioja": "Ameryka / Argentyna / La_Rioja",
  "Pacific/Tahiti": "Pacific / Tahiti",
  "Asia/Brunei": "Azja / Brunei",
  "Europe/Zagreb": "Europa / Zagrzeb",
  "America/Asuncion": "Ameryka / Asuncion",
  "Europe/Vienna": "Europa / Wiede\u0144",
  "Australia/Hobart": "Australia / Hobart",
  "America/Juneau": "Ameryka / Juneau",
  "America/Inuvik": "Ameryka / Inuvik",
  "America/Ojinaga": "Ameryka / Ojinaga",
  "Europe/Astrakhan": "Europa / Astrakhan",
  "Europe/Saratov": "Europa / Saratov",
  "Asia/Seoul": "Azja / Seul",
  "Indian/Comoro": "Indyjski / komoro",
  "Europe/Paris": "Europa / Pary\u017c",
  "Europe/Tallinn": "Europa / Tallinn",
  "Indian/Mahe": "Indyjski / Mahe",
  "America/Argentina/Jujuy": "Ameryka / Argentyna / Jujuy",
  "America/Creston": "Ameryka / Creston",
  "America/Adak": "Ameryka / Adak",
  "Asia/Singapore": "Azja / Singapur",
  "Africa/Nairobi": "Afryka / Nairobi",
  "America/Maceio": "Ameryka / Maceio",
  "Africa/Cairo": "Afryka / Kair",
  "Europe/Moscow": "Europa / Moskwa",
  "Antarctica/Palmer": "Antarktyda / Palmer",
  "Asia/Ulaanbaatar": "Azja / U\u0142an Bator",
  "America/Rainy_River": "Ameryka / Rainy_River",
  "Africa/Kampala": "Afryka / Kampala",
  "Asia/Colombo": "Azja / Kolombo",
  "Australia/Adelaide": "Australia / Adelaide",
  "America/Cambridge_Bay": "Ameryka / Cambridge_Bay",
  "Africa/Luanda": "Afryka / Luanda",
  "Pacific/Chatham": "Pacific / Chatham",
  "America/Indiana/Winamac": "Ameryka / Indiana / Winamac",
  "Asia/Tbilisi": "Azja / Tbilisi",
  "Europe/Gibraltar": "Europa / Gibraltar",
  "Asia/Karachi": "Azja / Karaczi",
  "Australia/Lord_Howe": "Australia / Lord_Howe",
  "America/Bahia_Banderas": "Ameryka / Bahia_Banderas",
  "America/Boa_Vista": "Ameryka / Boa_Vista",
  "America/Lima": "Ameryka / Lima",
  "Indian/Reunion": "Indian / Reunion",
  "America/Campo_Grande": "Ameryka / Campo_Grande",
  "Asia/Srednekolymsk": "Azja / Srednekolymsk",
  "America/Blanc-Sablon": "Ameryka / Blanc-Sablon",
  "Antarctica/Syowa": "Antarktyda / Syowa",
  "America/Jamaica": "Ameryka / Jamajka",
  "Europe/Kiev": "Europa / Kij\u00f3w",
  "Europe/Budapest": "Europa / Budapeszt",
  "Canada/Eastern": "Kanada / wschodnia",
  "Pacific/Midway": "Pacific / Midway",
  "America/Goose_Bay": "Ameryka / Goose_Bay",
  "Asia/Amman": "Azja / Amman",
  "Asia/Sakhalin": "Azja / Sakhalin",
  "Africa/Windhoek": "Afryka / Windhoek",
  "America/Sitka": "Ameryka / Sitka",
  "America/Guyana": "Ameryka / Gujana",
  "Pacific/Pohnpei": "Pacific / Pohnpei",
  "America/Sao_Paulo": "Ameryka / Sao_Paulo",
  "America/Lower_Princes": "Ameryka / Dolna_Rynki",
  "Australia/Perth": "Australia / Perth",
  "Africa/Djibouti": "Afryka / D\u017cibuti",
  "Asia/Jakarta": "Azja / D\u017cakarta",
  "Asia/Pyongyang": "Azja / Pyongyang",
  "Africa/Johannesburg": "Afryka / Johannesburg",
  "Antarctica/Troll": "Antarktyda / Troll",
  "Asia/Irkutsk": "Azja / Irkuck",
  "US/Pacific": "USA / Pacyfik",
  "Africa/Niamey": "Afryka / Niamey",
  "America/Belem": "Ameryka / Belem",
  "America/Indiana/Marengo": "Ameryka / Indiana / Marengo",
  "Africa/Nouakchott": "Afryka / Nawakszut",
  "Europe/Vilnius": "Europa / Wilno",
  "America/Cayenne": "Ameryka / Cayenne",
  "Africa/Mogadishu": "Afryka / Mogadiszu",
  "America/Kentucky/Monticello": "Ameryka / Kentucky / Monticello",
  "America/Rio_Branco": "Ameryka / Rio_Branco",
  "America/Cancun": "Ameryka / Cancun",
  "America/Havana": "Ameryka / Hawana",
  "Pacific/Guam": "Pacific / Guam",
  "Pacific/Kosrae": "Pacific / Kosrae",
  "Canada/Atlantic": "Kanada / Atlantyk",
  "US/Arizona": "USA / Arizona",
  "Atlantic/Azores": "Atlantycki / azorski",
  "Australia/Eucla": "Australia / Eucla",
  "Asia/Shanghai": "Azja / Szanghaj",
  "US/Alaska": "USA / Alaska",
  "America/Godthab": "Ameryka / Godthab",
  "Asia/Beirut": "Azja / Bejrut",
  "Africa/Maputo": "Afryka / Maputo",
  "Asia/Bahrain": "Azja / Bahrajn",
  "Asia/Ashgabat": "Azja / Aszchabad",
  "Asia/Riyadh": "Azja / Riyadh",
  "Europe/London": "Europa / Londyn",
  "America/Montevideo": "Ameryka / Montevideo",
  "America/Anguilla": "Ameryka / Anguilla",
  "Asia/Damascus": "Azja / Damaszek",
  "America/North_Dakota/Center": "Ameryka / North_Dakota / Centrum",
  "America/Indiana/Vevay": "Ameryka / Indiana / Vevay",
  "Atlantic/St_Helena": "Atlantic / St_Helena",
  "America/Barbados": "Ameryka / Barbados",
  "Europe/Vatican": "Europa / Watykan",
  "America/Indiana/Vincennes": "Ameryka / Indiana / Vincennes",
  "Asia/Almaty": "Azja / Almaty",
  "America/Santo_Domingo": "Ameryka / Santo_Domingo",
  "Africa/Brazzaville": "Afryka / Brazzaville",
  "America/Nome": "Ameryka / Nome",
  "Asia/Taipei": "Azja / Tajpej",
  "America/Yakutat": "Ameryka / Yakutat",
  "America/Argentina/Mendoza": "Ameryka / Argentyna / Mendoza",
  "Australia/Currie": "Australia / Currie",
  "Europe/Vaduz": "Europa / Vaduz",
  "Antarctica/Mawson": "Antarktyda / Mawson",
  "Asia/Kolkata": "Azja / Kolkata",
  "Africa/Maseru": "Afryka / Maseru",
  "America/Atikokan": "Ameryka / Atikokan",
  "Asia/Kuching": "Azja / Kuching",
  "Africa/Libreville": "Afryka / Libreville",
  "Africa/Freetown": "Afryka / Freetown",
  "Africa/Bissau": "Afryka / Bissau",
  "Europe/Samara": "Europa / Samara",
  "Europe/Amsterdam": "Europa / Amsterdam",
  "Europe/Tirane": "Europa / Tirane",
  "Pacific/Saipan": "Pacific / Saipan",
  "Africa/Abidjan": "Afryka / Abid\u017can",
  "Europe/Zaporozhye": "Europa / Zaporo\u017ce",
  "America/El_Salvador": "Ameryka / El_Salvador",
  "Europe/Madrid": "Europa / Madryt",
  "Africa/Juba": "Afryka / Juba",
  "America/Santiago": "Ameryka / Santiago",
  "America/Argentina/Buenos_Aires": "Ameryka / Argentyna / Buenos_Aires",
  "America/Argentina/San_Luis": "Ameryka / Argentyna / San_Luis",
  "Europe/Skopje": "Europa / Skopje",
  "Asia/Atyrau": "Azja / Atyrau",
  "America/Aruba": "Ameryka / Aruba",
  "America/Regina": "Ameryka / Regina",
  "Pacific/Chuuk": "Pacific / Chuuk",
  "Asia/Khandyga": "Azja / Khandyga",
  "Pacific/Funafuti": "Pacific / Funafuti",
  "America/Merida": "Ameryka / Merida",
  "America/Guatemala": "Ameryka / Gwatemala",
  "Africa/Sao_Tome": "Afryka / Sao_Tome",
  "Asia/Tomsk": "Azja / Tomsk",
  "Asia/Makassar": "Azja / Makassar",
  "Africa/Bujumbura": "Afryka / Bu\u017cumbura",
  "Europe/Chisinau": "Europa / Kiszyni\u00f3w",
  "America/Monterrey": "Ameryka / Monterrey",
  "Asia/Yekaterinburg": "Azja / Jekaterynburg",
  "US/Hawaii": "USA / Hawaje",
  "Antarctica/Casey": "Antarktyda / Casey",
  "Pacific/Enderbury": "Pacific / Enderbury",
  "America/Thule": "Ameryka / Thule",
  "America/St_Johns": "Ameryka / St_Johns",
  "America/Moncton": "Ameryka / Moncton",
  "Europe/Helsinki": "Europa / Helsinki",
  "Atlantic/Cape_Verde": "Atlantic / Cape_Verde",
  "America/Tegucigalpa": "Ameryka / Tegucigalpa",
  "Indian/Cocos": "Indyjska / kokosowa",
  "America/Boise": "Ameryka / Boise",
  "America/Guadeloupe": "Ameryka / Gwadelupa",
  "America/Nassau": "Ameryka / Nassau",
  "Europe/Prague": "Europa / Praga",
  "America/Halifax": "Ameryka / Halifax",
  "Asia/Hovd": "Azja / Hovd",
  "America/Manaus": "Ameryka / Manaus",
  "America/Rankin_Inlet": "Ameryka / Rankin_Inlet",
  "America/North_Dakota/Beulah": "Ameryka / North_Dakota / Beulah",
  "America/Chihuahua": "Ameryka / Chihuahua",
  "America/Iqaluit": "Ameryka / Iqaluit",
  "America/Argentina/Rio_Gallegos": "Ameryka / Argentyna / Rio_Gallegos",
  "Pacific/Gambier": "Pacyfik / Gambier",
  "Europe/Volgograd": "Europa / Wolgograd",
  "Africa/Bamako": "Afryka / Bamako",
  "Asia/Novokuznetsk": "Azja / Novokuznetsk",
  "Europe/Uzhgorod": "Europa / Uzgorod",
  "Africa/Banjul": "Afryka / Banjul",
  "Asia/Aqtau": "Azja / Aqtau",
  "Pacific/Palau": "Pacyfik / Palau",
  "Africa/Malabo": "Afryka / Malabo",
  "Europe/Minsk": "Europa / Mi\u0144sk",
  "Atlantic/Madeira": "Atlantic / Madeira",
  "Pacific/Noumea": "Pacific / Noumea",
  "Africa/Kinshasa": "Afryka / Kinszasa",
  "Europe/Malta": "Europa / Malta",
  "America/Argentina/Ushuaia": "Ameryka / Argentyna / Ushuaia",
  "Asia/Bangkok": "Azja / Bangkok",
  "Pacific/Niue": "Pacific / Niue",
  "Australia/Brisbane": "Australia / Brisbane",
  "America/Recife": "Ameryka / Recife",
  "Asia/Yerevan": "Azja / Erywa\u0144",
  "America/La_Paz": "Ameryka / La_Paz",
  "Asia/Urumqi": "Azja / Urumqi",
  "Africa/Lusaka": "Afryka / Lusaka",
  "Pacific/Guadalcanal": "Pacific / Guadalcanal",
  "America/Yellowknife": "Ameryka / Yellowknife",
  "Canada/Newfoundland": "Kanada / Nowa Fundlandia",
  "Asia/Vientiane": "Azja / Wientian",
  "Europe/Kaliningrad": "Europa / Kaliningrad",
  "Africa/Conakry": "Afryka / Konakry",
  "America/Argentina/Tucuman": "Ameryka / Argentyna / Tucuman",
  "Asia/Chita": "Azja / Chita",
  "Europe/Oslo": "Europa / Oslo",
  "America/St_Kitts": "Ameryka / St_Kitts",
  "America/Panama": "Ameryka / Panama",
  "Africa/Gaborone": "Afryka / Gaborone",
  "Asia/Hebron": "Azja / Hebron",
  "America/Guayaquil": "Ameryka / Guayaquil",
  "Asia/Kuala_Lumpur": "Azja / Kuala_Lumpur",
  "America/Menominee": "Ameryka / Menominee",
  "Asia/Kamchatka": "Azja / Kamczatka",
  "Asia/Vladivostok": "Azja / W\u0142adywostok",
  "America/Matamoros": "Ameryka / Matamoros",
  "Asia/Qatar": "Azja / Katar",
  "Asia/Dubai": "Azja / Dubaj",
  "Asia/Yakutsk": "Azja / Jakuck",
  "Asia/Omsk": "Azja / Omsk",
  "Africa/Bangui": "Afryka / Bangui",
  "UTC": "UTC",
  "America/Paramaribo": "Ameryka / Paramaribo",
  "Africa/Lubumbashi": "Afryka / Lubumbashi",
  "Pacific/Marquesas": "Pacific / Marquesas",
  "US/Central": "USA / Centrala",
  "Europe/Bratislava": "Europa / Bratys\u0142awa",
  "Asia/Anadyr": "Azja / Anadyr",
  "America/New_York": "Ameryka / New_York",
  "Pacific/Norfolk": "Pacific / Norfolk",
  "Pacific/Rarotonga": "Pacific / Rarotonga",
  "America/Dominica": "Ameryka / Dominika",
  "Africa/Porto-Novo": "Afryka / Porto-Novo",
  "Asia/Samarkand": "Azja / Samarkanda",
  "Asia/Dushanbe": "Azja / Dushanbe",
  "America/Kentucky/Louisville": "Ameryka / Kentucky / Louisville",
  "America/Toronto": "Ameryka / Toronto",
  "America/Bahia": "Ameryka / Bahia",
  "Indian/Maldives": "Indyjski / Malediwy",
  "Africa/Accra": "Afryka / Accra",
  "Asia/Muscat": "Azja / Muscat",
  "America/Edmonton": "Ameryka / Edmonton",
  "Pacific/Wake": "Pacyfik / Wake",
  "America/Indiana/Tell_City": "Ameryka / Indiana / Tell_City",
  "Australia/Darwin": "Australia / Darwin",
  "America/Whitehorse": "Ameryka / Whitehorse",
  "America/Swift_Current": "Ameryka / Swift_Current",
  "Europe/Copenhagen": "Europa / Kopenhaga",
  "America/Argentina/Salta": "Ameryka / Argentyna / Salta",
  "America/Montserrat": "Ameryka / Montserrat",
  "Europe/Simferopol": "Europa / Symferopol",
  "Africa/Blantyre": "Afryka / Blantyre",
  "America/Detroit": "Ameryka / Detroit",
  "America/Grenada": "Ameryka / Grenada",
  "Atlantic/Faroe": "Atlantic / Faroe",
  "America/Indiana/Petersburg": "Ameryka / Indiana / Petersburg",
  "Asia/Kathmandu": "Azja / Katmandu",
  "Asia/Pontianak": "Azja / Pontianak",
  "Europe/Athens": "Europa / Ateny",
  "America/Port-au-Prince": "Ameryka / Port-au-Prince",
  "America/Cayman": "Ameryka / Cayman",
  "Africa/Dar_es_Salaam": "Afryka / Dar_es_Salaam",
  "America/Curacao": "Ameryka / Curacao",
  "Indian/Kerguelen": "Indian / Kerguelen",
  "Africa/Khartoum": "Afryka / Chartum",
  "Asia/Manila": "Azja / Manila",
  "Africa/Lome": "Afryka / Lome",
  "Africa/Douala": "Afryka / Douala",
  "Europe/Rome": "Europa / Rzym",
  "America/Argentina/San_Juan": "Ameryka / Argentyna / San_Juan",
  "America/North_Dakota/New_Salem": "Ameryka / North_Dakota / New_Salem",
  "America/Kralendijk": "Ameryka / Kralendijk",
  "Pacific/Port_Moresby": "Pacific / Port_Moresby",
  "Europe/Jersey": "Europa / Jersey",
  "Europe/Andorra": "Europa / Andora",
  "Europe/Luxembourg": "Europa / Luksemburg",
  "Pacific/Honolulu": "Pacific / Honolulu",
  "America/St_Thomas": "Ameryka / St_Thomas",
  "Pacific/Majuro": "Pacific / Majuro",
  "Asia/Hong_Kong": "Azja / Hong_Kong",
  "Asia/Macau": "Azja / Makau",
  "Europe/Belgrade": "Europa / Belgrad",
  "Asia/Choibalsan": "Azja / Choibalsan",
  "Europe/Mariehamn": "Europa / Mariehamn",
  "Antarctica/McMurdo": "Antarktyda / McMurdo",
  "America/Thunder_Bay": "Ameryka / Thunder_Bay",
  "America/Los_Angeles": "Ameryka / Los_Angeles",
  "Asia/Kabul": "Azja / Kabul",
  "Indian/Antananarivo": "Indyjski / Antananarivo",
  "Europe/Sarajevo": "Europa / Sarajewo",
  "Atlantic/Reykjavik": "Atlantic / Reykjavik",
  "Asia/Nicosia": "Azja / Nikozja",
  "Asia/Barnaul": "Azja / Barnau\u0142",
  "Pacific/Tongatapu": "Pacific / Tongatapu",
  "America/Marigot": "Ameryka / Marigot",
  "Pacific/Pitcairn": "Pacific / Pitcairn",
  "Pacific/Easter": "Pacyfiku / Wielkanocy",
  "Atlantic/South_Georgia": "Atlantycki / po\u0142udniowo-gruzja",
  "Africa/El_Aaiun": "Afryka / El_Aaiun",
  "Europe/Kirov": "Europa / Kirov",
  "Europe/Dublin": "Europa / Dublin",
  "America/Dawson_Creek": "Ameryka / Dawson_Creek",
  "Antarctica/Vostok": "Antarktyda / Vostok",
  "Europe/Bucharest": "Europa / Bukareszt",
  "America/Porto_Velho": "Ameryka / Porto_Velho",
  "Europe/Monaco": "Europa / Monako",
  "Asia/Bishkek": "Azja / Biszkek",
  "Africa/Ceuta": "Afryka / Ceuta",
  "America/Winnipeg": "Ameryka / Winnipeg",
  "Asia/Aqtobe": "Azja / Aqtobe",
  "Africa/Dakar": "Afryka / Dakar",
  "America/Fortaleza": "Ameryka / Fortaleza",
  "Pacific/Tarawa": "Pacyfiku / Tarawie",
  "America/Dawson": "Ameryka / Dawson",
  "Africa/Addis_Ababa": "Afryka / Addis_Ababa",
  "Pacific/Efate": "Pacific / Efate",
  "Pacific/Johnston": "Pacific / Johnston",
  "GMT": "GMT",
  "Asia/Qyzylorda": "Azja / Qyzylorda",
  "Europe/San_Marino": "Europa / San_Marino",
  "Asia/Jerusalem": "Azja / Jerozolima",
  "Pacific/Auckland": "Pacific / Auckland",
  "America/Metlakatla": "Ameryka / Metlakatla",
  "America/Tortola": "Ameryka / Tortola",
  "America/Denver": "Ameryka / Denver",
  "Indian/Chagos": "Indyjski / Chagos",
  "America/Glace_Bay": "Ameryka / Glace_Bay",
  "Pacific/Bougainville": "Pacific / Bougainville",
  "America/Hermosillo": "Ameryka / Hermosillo",
  "Africa/Tunis": "Afryka / Tunis",
  "Europe/Ulyanovsk": "Europa / Ulyanovsk",
  "Asia/Ust-Nera": "Azja / Ust-Nera",
  "America/Resolute": "Ameryka / zdecydowana",
  "Asia/Gaza": "Azja / Gazza",
  "US/Mountain": "USA / G\u00f3ra",
  "Antarctica/DumontDUrville": "Antarktyda / DumontDUrville",
  "America/Argentina/Catamarca": "Ameryka / Argentyna / Catamarca",
  "America/Indiana/Knox": "Ameryka / Indiana / Knox",
  "Asia/Novosibirsk": "Azja / Nowosybirsk",
  "Africa/Kigali": "Afryka / Kigali",
  "US/Eastern": "USA / wschodnia",
  "America/Grand_Turk": "Ameryka / Grand_Turk",
  "Canada/Central": "Kanada / Central",
  "Africa/Lagos": "Afryka / Lagos",
  "Europe/Sofia": "Europa / Sofia",
  "Africa/Tripoli": "Afryka / Tripoli",
  "America/Anchorage": "Ameryka / Anchorage",
  "Pacific/Nauru": "Pacific / Nauru"
}