{
  "AppSignup": "Aplikasi ieu hasil dijieun.",
  "AvatarDeleted": "Avatar ieu hasil dihapus.",
  "AvatarUpdated": "Avatar ieu hasil diunggah.",
  "CodeSent": "Hiji kodeu konfirmasi geus dikirim ka alat Anjeun.",
  "DeviceVerified": "Alat geus diverifikasi.",
  "GlobalLogout": "Kaluar dina sadaya alat. Pendak deui engk\u00e9.",
  "LocalLogout": "Kaluar dina alat ieu. Pendak deui engk\u00e9.",
  "PasswordUpdated": "Sandi hasil dirop\u00e9a.",
  "ProfileUpdated": "Profil ieu hasil dirop\u00e9a.",
  "SignupPassword": "Akun ieu hasil dijieun.",
  "TicketSent": "Hiji email geus dikirim ka tim rojongan."
}